quic_portal-0.1.13.dist-info/METADATA
quic_portal-0.1.13.dist-info/WHEEL
quic_portal-0.1.13.dist-info/licenses/LICENSE
quic_portal/__init__.py
quic_portal/_core.abi3.so
quic_portal/exceptions.py
quic_portal/nat.py
quic_portal/portal.py
quic_portal-0.1.13.dist-info/RECORD
