Metadata-Version: 2.4
Name: quic-portal
Version: 0.1.13
Classifier: Development Status :: 3 - Alpha
Classifier: Intended Audience :: Developers
Classifier: License :: OSI Approved :: MIT License
Classifier: Programming Language :: Python :: 3
Classifier: Programming Language :: Python :: 3.9
Classifier: Programming Language :: Python :: 3.10
Classifier: Programming Language :: Python :: 3.11
Classifier: Programming Language :: Python :: 3.12
Classifier: Programming Language :: Rust
Classifier: Topic :: Internet
Classifier: Topic :: System :: Networking
Requires-Dist: modal>=1.1.0 ; extra == 'modal'
Requires-Dist: pytest>=7.0 ; extra == 'dev'
Requires-Dist: pytest-asyncio>=0.21.0 ; extra == 'dev'
Requires-Dist: black>=23.0 ; extra == 'dev'
Requires-Dist: ruff>=0.1.0 ; extra == 'dev'
Requires-Dist: mypy>=1.0 ; extra == 'dev'
Requires-Dist: modal>=1.1.0 ; extra == 'dev'
Provides-Extra: modal
Provides-Extra: dev
License-File: LICENSE
Summary: QUIC library with NAT traversal
Keywords: quic,networking,nat-traversal,p2p,communication
Author-email: Richard Gong <richard@modal.com>, Daniel Shaar <daniel@modal.com>
License: MIT
Requires-Python: >=3.9
Project-URL: Homepage, https://github.com/gongy/quic-portal
Project-URL: Repository, https://github.com/gongy/quic-portal
Project-URL: Documentation, https://github.com/gongy/quic-portal#readme
Project-URL: Bug Tracker, https://github.com/gongy/quic-portal/issues
